geoshaha/__init__.py
geoshaha/geoshaha.py
geoshaha-0.0.2.dist-info/LICENSE
geoshaha-0.0.2.dist-info/METADATA
geoshaha-0.0.2.dist-info/WHEEL
geoshaha-0.0.2.dist-info/top_level.txt
geoshaha-0.0.2.dist-info/RECORD
