Metadata-Version: 2.1
Name: geoshaha
Version: 0.0.2
Summary: Python Boilerplate contains all the boilerplate you need to create a Python package.
Home-page: https://github.com/giswqs/geoshaha
Author: Qiusheng Wu
Author-email: giswqs@gmail.com
License: MIT license
Keywords: geoshaha
Classifier: Development Status :: 2 - Pre-Alpha
Classifier: Intended Audience :: Developers
Classifier: License :: OSI Approved :: MIT License
Classifier: Natural Language :: English
Classifier: Programming Language :: Python :: 3
Classifier: Programming Language :: Python :: 3.7
Classifier: Programming Language :: Python :: 3.8
Classifier: Programming Language :: Python :: 3.9
Classifier: Programming Language :: Python :: 3.10
Requires-Python: >=3.7
License-File: LICENSE
